{"name":"Lux","count":807,"winRate":0.4758,"children":[{"name":"Mejai's Soulstealer","itemId":"3041","count":177,"winRate":0.5,"children":[{"name":"Rabadon's Deathcap","itemId":"3089","count":37,"winRate":0.5,"children":[{"name":"Void Staff","itemId":"3135","count":5,"winRate":1,"children":[]},{"name":"Zhonya's Hourglass","itemId":"3157","count":12,"winRate":0.4,"children":[{"name":"Void Staff","itemId":"3135","count":4,"winRate":0,"children":[]},{"name":"Luden's Echo","itemId":"3285","count":8,"winRate":0.5,"children":[]}]},{"name":"Morellonomicon","itemId":"3165","count":5,"winRate":0.5,"children":[{"name":"Zhonya's Hourglass","itemId":"3157","count":5,"winRate":1,"children":[]}]},{"name":"Luden's Echo","itemId":"3285","count":15,"winRate":0.5,"children":[{"name":"Void Staff","itemId":"3135","count":8,"winRate":1,"children":[]},{"name":"Zhonya's Hourglass","itemId":"3157","count":8,"winRate":0,"children":[]}]}]},{"name":"Morellonomicon","itemId":"3165","count":47,"winRate":0.48,"children":[{"name":"Rabadon's Deathcap","itemId":"3089","count":18,"winRate":0.5,"children":[{"name":"Zhonya's Hourglass","itemId":"3157","count":9,"winRate":0,"children":[]},{"name":"Luden's Echo","itemId":"3285","count":9,"winRate":0.5,"children":[{"name":"Zhonya's Hourglass","itemId":"3157","count":9,"winRate":0,"children":[]}]}]},{"name":"Lich Bane","itemId":"3100","count":3,"winRate":0,"children":[{"name":"Rabadon's Deathcap","itemId":"3089","count":3,"winRate":0,"children":[{"name":"Luden's Echo","itemId":"3285","count":3,"winRate":0,"children":[]}]}]},{"name":"Void Staff","itemId":"3135","count":6,"winRate":0.5,"children":[{"name":"Luden's Echo","itemId":"3285","count":6,"winRate":1,"children":[]}]},{"name":"Luden's Echo","itemId":"3285","count":21,"winRate":0.4286,"children":[{"name":"Rabadon's Deathcap","itemId":"3089","count":21,"winRate":0.5,"children":[{"name":"Void Staff","itemId":"3135","count":21,"winRate":1,"children":[]}]}]}]},{"name":"Athene's Unholy Grail","itemId":"3174","count":30,"winRate":0.75,"children":[{"name":"Rabadon's Deathcap","itemId":"3089","count":15,"winRate":0.8333,"children":[{"name":"Void Staff","itemId":"3135","count":8,"winRate":1,"children":[]},{"name":"Luden's Echo","itemId":"3285","count":8,"winRate":1,"children":[]}]},{"name":"Zhonya's Hourglass","itemId":"3157","count":3,"winRate":1,"children":[]},{"name":"Morellonomicon","itemId":"3165","count":3,"winRate":1,"children":[{"name":"Luden's Echo","itemId":"3285","count":3,"winRate":1,"children":[]}]},{"name":"Luden's Echo","itemId":"3285","count":10,"winRate":0.5,"children":[{"name":"Abyssal Scepter","itemId":"3001","count":5,"winRate":0,"children":[]},{"name":"Rabadon's Deathcap","itemId":"3089","count":5,"winRate":0,"children":[]}]}]},{"name":"Luden's Echo","itemId":"3285","count":63,"winRate":0.5588,"children":[{"name":"Rod of Ages","itemId":"3027","count":8,"winRate":1,"children":[]},{"name":"Rabadon's Deathcap","itemId":"3089","count":32,"winRate":0.625,"children":[{"name":"Void Staff","itemId":"3135","count":9,"winRate":0.5,"children":[]},{"name":"Zhonya's Hourglass","itemId":"3157","count":18,"winRate":0.75,"children":[{"name":"Banshee's Veil","itemId":"3102","count":18,"winRate":1,"children":[]}]},{"name":"Morellonomicon","itemId":"3165","count":5,"winRate":1,"children":[]}]},{"name":"Zhonya's Hourglass","itemId":"3157","count":12,"winRate":1,"children":[{"name":"Rabadon's Deathcap","itemId":"3089","count":6,"winRate":1,"children":[{"name":"Twin Shadows","itemId":"3023","count":6,"winRate":1,"children":[]}]},{"name":"Morellonomicon","itemId":"3165","count":6,"winRate":1,"children":[]}]},{"name":"Morellonomicon","itemId":"3165","count":12,"winRate":0.6667,"children":[{"name":"Void Staff","itemId":"3135","count":12,"winRate":0,"children":[]}]}]}]},{"name":"Morellonomicon","itemId":"3165","count":192,"winRate":0.4818,"children":[{"name":"Mejai's Soulstealer","itemId":"3041","count":36,"winRate":0.9333,"children":[{"name":"Rabadon's Deathcap","itemId":"3089","count":4,"winRate":1,"children":[]},{"name":"Void Staff","itemId":"3135","count":4,"winRate":1,"children":[{"name":"Athene's Unholy Grail","itemId":"3174","count":4,"winRate":1,"children":[{"name":"Rabadon's Deathcap","itemId":"3089","count":4,"winRate":1,"children":[]}]}]},{"name":"Zhonya's Hourglass","itemId":"3157","count":4,"winRate":1,"children":[]},{"name":"Luden's Echo","itemId":"3285","count":24,"winRate":1,"children":[{"name":"Rabadon's Deathcap","itemId":"3089","count":16,"winRate":1,"children":[{"name":"Zhonya's Hourglass","itemId":"3157","count":16,"winRate":1,"children":[{"name":"Void Staff","itemId":"3135","count":16,"winRate":1,"children":[]}]}]},{"name":"Void Staff","itemId":"3135","count":4,"winRate":1,"children":[]},{"name":"Zhonya's Hourglass","itemId":"3157","count":4,"winRate":1,"children":[{"name":"Rabadon's Deathcap","itemId":"3089","count":4,"winRate":1,"children":[{"name":"Banshee's Veil","itemId":"3102","count":4,"winRate":1,"children":[]}]}]}]}]},{"name":"Rabadon's Deathcap","itemId":"3089","count":51,"winRate":0.4762,"children":[{"name":"Void Staff","itemId":"3135","count":6,"winRate":1,"children":[]},{"name":"Zhonya's Hourglass","itemId":"3157","count":23,"winRate":0.75,"children":[{"name":"Void Staff","itemId":"3135","count":8,"winRate":1,"children":[{"name":"Luden's Echo","itemId":"3285","count":8,"winRate":1,"children":[]}]},{"name":"Athene's Unholy Grail","itemId":"3174","count":8,"winRate":1,"children":[]},{"name":"Luden's Echo","itemId":"3285","count":8,"winRate":0,"children":[]}]},{"name":"Morellonomicon","itemId":"3165","count":6,"winRate":0,"children":[{"name":"Rabadon's Deathcap","itemId":"3089","count":6,"winRate":0,"children":[]}]},{"name":"Luden's Echo","itemId":"3285","count":17,"winRate":0.6667,"children":[{"name":"Mejai's Soulstealer","itemId":"3041","count":9,"winRate":0,"children":[{"name":"Rabadon's Deathcap","itemId":"3089","count":9,"winRate":0,"children":[]}]},{"name":"Void Staff","itemId":"3135","count":9,"winRate":1,"children":[{"name":"Zhonya's Hourglass","itemId":"3157","count":9,"winRate":1,"children":[]}]}]}]},{"name":"Void Staff","itemId":"3135","count":24,"winRate":0.3,"children":[{"name":"Rabadon's Deathcap","itemId":"3089","count":12,"winRate":1,"children":[{"name":"Zhonya's Hourglass","itemId":"3157","count":6,"winRate":1,"children":[]},{"name":"Athene's Unholy Grail","itemId":"3174","count":6,"winRate":1,"children":[{"name":"Luden's Echo","itemId":"3285","count":6,"winRate":1,"children":[]}]}]},{"name":"Luden's Echo","itemId":"3285","count":12,"winRate":0,"children":[]}]},{"name":"Luden's Echo","itemId":"3285","count":80,"winRate":0.4242,"children":[{"name":"Rabadon's Deathcap","itemId":"3089","count":60,"winRate":0.4667,"children":[{"name":"Mejai's Soulstealer","itemId":"3041","count":8,"winRate":1,"children":[]},{"name":"Banner of Command","itemId":"3060","count":8,"winRate":0,"children":[{"name":"Liandry's Torment","itemId":"3151","count":8,"winRate":0,"children":[]}]},{"name":"Void Staff","itemId":"3135","count":30,"winRate":0.75,"children":[{"name":"Lich Bane","itemId":"3100","count":15,"winRate":1,"children":[]},{"name":"Morellonomicon","itemId":"3165","count":15,"winRate":1,"children":[{"name":"Zhonya's Hourglass","itemId":"3157","count":15,"winRate":1,"children":[]}]}]},{"name":"Zhonya's Hourglass","itemId":"3157","count":15,"winRate":0,"children":[{"name":"Abyssal Scepter","itemId":"3001","count":8,"winRate":0,"children":[]},{"name":"Void Staff","itemId":"3135","count":8,"winRate":0,"children":[{"name":"Rylai's Crystal Scepter","itemId":"3116","count":8,"winRate":0,"children":[]}]}]}]},{"name":"Banshee's Veil","itemId":"3102","count":4,"winRate":0,"children":[{"name":"Zhonya's Hourglass","itemId":"3157","count":4,"winRate":0,"children":[]}]},{"name":"Zhonya's Hourglass","itemId":"3157","count":16,"winRate":0.5,"children":[{"name":"Banshee's Veil","itemId":"3102","count":16,"winRate":0,"children":[]}]}]}]},{"name":"Athene's Unholy Grail","itemId":"3174","count":215,"winRate":0.4706,"children":[{"name":"Mejai's Soulstealer","itemId":"3041","count":33,"winRate":0.5333,"children":[{"name":"Rabadon's Deathcap","itemId":"3089","count":17,"winRate":0.5,"children":[]},{"name":"Banshee's Veil","itemId":"3102","count":4,"winRate":0,"children":[]},{"name":"Zhonya's Hourglass","itemId":"3157","count":4,"winRate":0,"children":[{"name":"Rabadon's Deathcap","itemId":"3089","count":4,"winRate":0,"children":[{"name":"Void Staff","itemId":"3135","count":4,"winRate":0,"children":[]}]}]},{"name":"Luden's Echo","itemId":"3285","count":8,"winRate":1,"children":[{"name":"Rabadon's Deathcap","itemId":"3089","count":8,"winRate":1,"children":[]}]}]},{"name":"Rabadon's Deathcap","itemId":"3089","count":82,"winRate":0.4324,"children":[{"name":"Void Staff","itemId":"3135","count":21,"winRate":0.25,"children":[{"name":"Zhonya's Hourglass","itemId":"3157","count":11,"winRate":0.5,"children":[]},{"name":"Luden's Echo","itemId":"3285","count":11,"winRate":0,"children":[{"name":"Abyssal Scepter","itemId":"3001","count":11,"winRate":0,"children":[{"name":"Morellonomicon","itemId":"3165","count":11,"winRate":0,"children":[]}]}]}]},{"name":"Zhonya's Hourglass","itemId":"3157","count":21,"winRate":0.5,"children":[{"name":"Void Staff","itemId":"3135","count":21,"winRate":1,"children":[]}]},{"name":"Morellonomicon","itemId":"3165","count":15,"winRate":0.6667,"children":[{"name":"Zhonya's Hourglass","itemId":"3157","count":15,"winRate":1,"children":[]}]},{"name":"Luden's Echo","itemId":"3285","count":26,"winRate":0.6,"children":[{"name":"Morellonomicon","itemId":"3165","count":26,"winRate":1,"children":[]}]}]},{"name":"Zhonya's Hourglass","itemId":"3157","count":20,"winRate":0.5556,"children":[{"name":"Void Staff","itemId":"3135","count":13,"winRate":1,"children":[{"name":"Rabadon's Deathcap","itemId":"3089","count":13,"winRate":1,"children":[]}]},{"name":"Luden's Echo","itemId":"3285","count":7,"winRate":0,"children":[]}]},{"name":"Luden's Echo","itemId":"3285","count":80,"winRate":0.6667,"children":[{"name":"Mejai's Soulstealer","itemId":"3041","count":19,"winRate":0.6667,"children":[{"name":"Rabadon's Deathcap","itemId":"3089","count":6,"winRate":1,"children":[{"name":"Zhonya's Hourglass","itemId":"3157","count":6,"winRate":1,"children":[]}]},{"name":"Void Staff","itemId":"3135","count":6,"winRate":1,"children":[{"name":"Rabadon's Deathcap","itemId":"3089","count":6,"winRate":1,"children":[]}]},{"name":"Zhonya's Hourglass","itemId":"3157","count":6,"winRate":0,"children":[{"name":"Void Staff","itemId":"3135","count":6,"winRate":0,"children":[{"name":"Morellonomicon","itemId":"3165","count":6,"winRate":0,"children":[]}]}]}]},{"name":"Rabadon's Deathcap","itemId":"3089","count":26,"winRate":0.75,"children":[{"name":"Zhonya's Hourglass","itemId":"3157","count":13,"winRate":1,"children":[]},{"name":"Morellonomicon","itemId":"3165","count":13,"winRate":0,"children":[]}]},{"name":"Void Staff","itemId":"3135","count":19,"winRate":0.5,"children":[{"name":"Rabadon's Deathcap","itemId":"3089","count":19,"winRate":0.5,"children":[{"name":"Zhonya's Hourglass","itemId":"3157","count":19,"winRate":1,"children":[]}]}]},{"name":"Zhonya's Hourglass","itemId":"3157","count":16,"winRate":0.6,"children":[{"name":"Void Staff","itemId":"3135","count":16,"winRate":0.5,"children":[{"name":"Rabadon's Deathcap","itemId":"3089","count":16,"winRate":0,"children":[]}]}]}]}]},{"name":"Luden's Echo","itemId":"3285","count":223,"winRate":0.4403,"children":[{"name":"Mejai's Soulstealer","itemId":"3041","count":47,"winRate":0.5714,"children":[{"name":"Rabadon's Deathcap","itemId":"3089","count":22,"winRate":0.5,"children":[{"name":"Lich Bane","itemId":"3100","count":6,"winRate":1,"children":[{"name":"Guardian Angel","itemId":"3026","count":6,"winRate":1,"children":[]}]},{"name":"Void Staff","itemId":"3135","count":6,"winRate":0,"children":[]},{"name":"Zhonya's Hourglass","itemId":"3157","count":11,"winRate":0.5,"children":[{"name":"Rylai's Crystal Scepter","itemId":"3116","count":11,"winRate":1,"children":[]}]}]},{"name":"Zhonya's Hourglass","itemId":"3157","count":14,"winRate":0.75,"children":[{"name":"Void Staff","itemId":"3135","count":14,"winRate":0,"children":[]}]},{"name":"Morellonomicon","itemId":"3165","count":11,"winRate":1,"children":[{"name":"Rabadon's Deathcap","itemId":"3089","count":11,"winRate":1,"children":[{"name":"Void Staff","itemId":"3135","count":11,"winRate":1,"children":[]}]}]}]},{"name":"Rabadon's Deathcap","itemId":"3089","count":74,"winRate":0.4848,"children":[{"name":"Infinity Edge","itemId":"3031","count":5,"winRate":1,"children":[]},{"name":"Void Staff","itemId":"3135","count":19,"winRate":0,"children":[{"name":"Mejai's Soulstealer","itemId":"3041","count":19,"winRate":0,"children":[]}]},{"name":"Zhonya's Hourglass","itemId":"3157","count":32,"winRate":0.5714,"children":[{"name":"Rabadon's Deathcap","itemId":"3089","count":16,"winRate":0,"children":[]},{"name":"Rylai's Crystal Scepter","itemId":"3116","count":16,"winRate":0,"children":[]}]},{"name":"Morellonomicon","itemId":"3165","count":19,"winRate":0.75,"children":[{"name":"Void Staff","itemId":"3135","count":10,"winRate":1,"children":[{"name":"Banshee's Veil","itemId":"3102","count":10,"winRate":1,"children":[]}]},{"name":"Athene's Unholy Grail","itemId":"3174","count":10,"winRate":1,"children":[{"name":"Void Staff","itemId":"3135","count":10,"winRate":1,"children":[]}]}]}]},{"name":"Zhonya's Hourglass","itemId":"3157","count":47,"winRate":0.3333,"children":[{"name":"Frozen Mallet","itemId":"3022","count":4,"winRate":0,"children":[]},{"name":"Rabadon's Deathcap","itemId":"3089","count":21,"winRate":0.4,"children":[{"name":"Banshee's Veil","itemId":"3102","count":7,"winRate":1,"children":[]},{"name":"Morellonomicon","itemId":"3165","count":7,"winRate":1,"children":[]},{"name":"Athene's Unholy Grail","itemId":"3174","count":7,"winRate":0,"children":[]}]},{"name":"Lich Bane","itemId":"3100","count":9,"winRate":0.5,"children":[{"name":"Void Staff","itemId":"3135","count":9,"winRate":1,"children":[]}]},{"name":"Morellonomicon","itemId":"3165","count":13,"winRate":0.6667,"children":[{"name":"Rabadon's Deathcap","itemId":"3089","count":9,"winRate":0.5,"children":[]},{"name":"Banshee's Veil","itemId":"3102","count":4,"winRate":1,"children":[{"name":"Athene's Unholy Grail","itemId":"3174","count":4,"winRate":1,"children":[]}]}]}]},{"name":"Morellonomicon","itemId":"3165","count":56,"winRate":0.52,"children":[{"name":"Rabadon's Deathcap","itemId":"3089","count":28,"winRate":0.5,"children":[{"name":"Void Staff","itemId":"3135","count":9,"winRate":1,"children":[]},{"name":"Zhonya's Hourglass","itemId":"3157","count":19,"winRate":0.5,"children":[{"name":"Rylai's Crystal Scepter","itemId":"3116","count":19,"winRate":1,"children":[]}]}]},{"name":"Void Staff","itemId":"3135","count":9,"winRate":0.5,"children":[{"name":"Zhonya's Hourglass","itemId":"3157","count":9,"winRate":1,"children":[]}]},{"name":"Zhonya's Hourglass","itemId":"3157","count":14,"winRate":1,"children":[{"name":"Mejai's Soulstealer","itemId":"3041","count":5,"winRate":1,"children":[]},{"name":"Rabadon's Deathcap","itemId":"3089","count":5,"winRate":1,"children":[]},{"name":"Void Staff","itemId":"3135","count":5,"winRate":1,"children":[]}]},{"name":"Athene's Unholy Grail","itemId":"3174","count":5,"winRate":1,"children":[]}]}]}],"champStrKey":"Lux"}